{
  "lastUpdated": "2026-07-14T19:33:20+05:30",
  "sectors": [
    {
      "name": "Automobile and Auto Components",
      "medianPe": 39.7,
      "members": [
        "MARUTI",
        "M&M",
        "BAJAJ-AUTO",
        "EICHERMOT",
        "TVSMOTOR",
        "HYUNDAI",
        "MOTHERSON",
        "TMPV",
        "BOSCHLTD",
        "BHARATFORG",
        "HEROMOTOCO",
        "UNOMINDA",
        "SCHAEFFLER",
        "TIINDIA",
        "MRF",
        "ATHERENERG",
        "BALKRISIND",
        "SONACOMS",
        "ENDURANCE",
        "EXIDEIND",
        "APOLLOTYRE",
        "ZFCVINDIA",
        "MSUMI",
        "CRAFTSMAN",
        "ASAHIINDIA",
        "FORCEMOT",
        "GABRIEL",
        "BELRISE",
        "CIEINDIA",
        "OLAELEC",
        "ARE&M",
        "JBMA",
        "MINDACORP",
        "CEATLTD",
        "JKTYRE",
        "OLECTRA",
        "RKFORGE",
        "TENNIND"
      ]
    },
    {
      "name": "Capital Goods",
      "medianPe": 53.7,
      "members": [
        "BEL",
        "HAL",
        "TMCV",
        "CUMMINSIND",
        "ABB",
        "POWERINDIA",
        "POLYCAB",
        "CGPOWER",
        "BHEL",
        "SIEMENS",
        "ENRIN",
        "GVT&D",
        "MAZDOCK",
        "ASHOKLEY",
        "WAAREEENER",
        "SUZLON",
        "APARINDS",
        "APLAPOLLO",
        "PREMIERENE",
        "THERMAX",
        "KEI",
        "BDL",
        "AIAENG",
        "WELCORP",
        "CPPLUS",
        "SUPREMEIND",
        "COCHINSHIP",
        "ASTRAL",
        "KIRLOSENG",
        "HONAUT",
        "SCHNEIDER",
        "ESCORTS",
        "GRSE",
        "SHYAMMETL",
        "SYRMA",
        "RRKABEL",
        "PTCIL",
        "TIMKEN",
        "DATAPATTNS",
        "EMMVEE",
        "KAYNES",
        "HBLENGINE",
        "CARBORUNIV",
        "TRITURBINE",
        "ELGIEQUIP",
        "JYOTICNC",
        "GALLANTT",
        "JINDALSAW",
        "GPIL",
        "ZENTEC",
        "FINCABLES",
        "BEML",
        "USHAMART",
        "INOXWIND",
        "TEGA",
        "GRAPHITE",
        "ACE",
        "TITAGARH",
        "ELECON",
        "HEG",
        "JWL",
        "TARIL",
        "RHIM"
      ]
    },
    {
      "name": "Chemicals",
      "medianPe": 41.9,
      "members": [
        "SOLARINDS",
        "PIDILITIND",
        "SRF",
        "COROMANDEL",
        "LINDEINDIA",
        "FACT",
        "UPL",
        "FLUOROCHEM",
        "NAVINFLUOR",
        "PIIND",
        "HSCL",
        "SUMICHEM",
        "DEEPAKNTR",
        "DEEPAKFERT",
        "BAYERCROP",
        "CHAMBLFERT",
        "TATACHEM",
        "ATUL",
        "AARTIIND",
        "PARADEEP",
        "ANURAS",
        "SPLPETRO",
        "PCBL",
        "JUBLINGREA",
        "CLEAN"
      ]
    },
    {
      "name": "Construction",
      "medianPe": 27.0,
      "members": [
        "LT",
        "RVNL",
        "NBCC",
        "CEMPRO",
        "IRB",
        "KPIL",
        "KEC",
        "ENGINERSIN",
        "IRCON",
        "TECHNOE",
        "AFCONS",
        "RITES",
        "NCC"
      ]
    },
    {
      "name": "Construction Materials",
      "medianPe": 31.5,
      "members": [
        "ULTRACEMCO",
        "GRASIM",
        "AMBUJACEM",
        "SHREECEM",
        "JKCEMENT",
        "DALBHARAT",
        "ACC",
        "RAMCOCEM",
        "JSWCEMENT",
        "INDIACEM",
        "NUVOCO"
      ]
    },
    {
      "name": "Consumer Durables",
      "medianPe": 59.6,
      "members": [
        "TITAN",
        "ASIANPAINT",
        "LGEINDIA",
        "DIXON",
        "HAVELLS",
        "BERGEPAINT",
        "KALYANKJIL",
        "VOLTAS",
        "BLUESTARCO",
        "AMBER",
        "KAJARIACER",
        "PGEL",
        "CROMPTON",
        "JSWDULUX",
        "WHIRLPOOL",
        "BATAINDIA"
      ]
    },
    {
      "name": "Consumer Services",
      "medianPe": 53.8,
      "members": [
        "ETERNAL",
        "DMART",
        "TRENT",
        "INDHOTEL",
        "NYKAA",
        "LENSKART",
        "MEESHO",
        "NAUKRI",
        "SWIGGY",
        "VMM",
        "PWL",
        "IRCTC",
        "ITCHOTELS",
        "JUBLFOOD",
        "EIHOTEL",
        "URBANCO",
        "TRAVELFOOD",
        "THELEELA",
        "TBOTEK",
        "DEVYANI",
        "CARTRADE",
        "ABLBL",
        "INDIAMART",
        "FIRSTCRY",
        "BLS",
        "LEMONTREE",
        "ABFRL",
        "SAPPHIRE",
        "CHALET"
      ]
    },
    {
      "name": "Diversified",
      "medianPe": 37.5,
      "members": [
        "GODREJIND",
        "3MINDIA",
        "DCMSHRIRAM"
      ]
    },
    {
      "name": "Fast Moving Consumer Goods",
      "medianPe": 48.9,
      "members": [
        "HINDUNILVR",
        "ITC",
        "NESTLEIND",
        "VBL",
        "BRITANNIA",
        "MARICO",
        "GODREJCP",
        "TATACONSUM",
        "UNITDSPR",
        "DABUR",
        "COLPAL",
        "RADICO",
        "PATANJALI",
        "UBL",
        "GODFRYPHLP",
        "GILLETTE",
        "AWL",
        "ZYDUSWELL",
        "EMAMILTD",
        "ABDL",
        "CCL",
        "BIKAJI",
        "HONASA",
        "DOMS",
        "EIDPARRY",
        "LTFOODS",
        "BALRAMCHIN",
        "BBTC"
      ]
    },
    {
      "name": "Financial Services",
      "medianPe": 25.5,
      "members": [
        "HDFCBANK",
        "ICICIBANK",
        "SBIN",
        "BAJFINANCE",
        "LICI",
        "AXISBANK",
        "KOTAKBANK",
        "BAJAJFINSV",
        "SHRIRAMFIN",
        "SBILIFE",
        "ICICIAMC",
        "JIOFIN",
        "CHOLAFIN",
        "BSE",
        "TATACAP",
        "PFC",
        "UNIONBANK",
        "GROWW",
        "BANKBARODA",
        "MUTHOOTFIN",
        "HDFCLIFE",
        "PNB",
        "CANBK",
        "BAJAJHLDNG",
        "IRFC",
        "HDFCAMC",
        "INDIANB",
        "ABCAPITAL",
        "IDBI",
        "RECLTD",
        "ICICIGI",
        "PAYTM",
        "FEDERALBNK",
        "LTF",
        "AUBANK",
        "INDUSINDBK",
        "NAM-INDIA",
        "YESBANK",
        "MCX",
        "ICICIPRULI",
        "BAJAJHFL",
        "POLICYBZR",
        "IDFCFIRSTB",
        "BANKINDIA",
        "IOB",
        "GICRE",
        "HDBFS",
        "MAHABANK",
        "RBLBANK",
        "SBICARD",
        "MOTILALOFS",
        "MFSL",
        "SUNDARMFIN",
        "PIRAMALFIN",
        "360ONE",
        "M&MFIN",
        "AIIL",
        "HUDCO",
        "POONAWALLA",
        "STARHEALTH",
        "NUVAMA",
        "ANANDRATHI",
        "IREDA",
        "TATAINVEST",
        "BANDHANBNK",
        "ABSLAMC",
        "UCOBANK",
        "CHOLAHLDNG",
        "MANAPPURAM",
        "ANGELONE",
        "LICHSGFIN",
        "CDSL",
        "NIACL",
        "CRISIL",
        "CENTRALBK",
        "KARURVYSYA",
        "PNBHOUSING",
        "GODIGIT",
        "CGCL",
        "CREDITACC",
        "IIFL",
        "AADHARHFC",
        "CUB",
        "IFCI",
        "J&KBANK",
        "CAMS",
        "SAMMAANCAP",
        "CHOICEIN",
        "PINELABS",
        "NIVABUPA",
        "FIVESTAR",
        "KFINTECH",
        "APTUS",
        "CANHLIFE",
        "HOMEFIRST",
        "UTIAMC",
        "CANFINHOME",
        "JMFINANCIL",
        "AAVAS",
        "IEX",
        "SBFC"
      ]
    },
    {
      "name": "Healthcare",
      "medianPe": 51.9,
      "members": [
        "SUNPHARMA",
        "DIVISLAB",
        "TORNTPHARM",
        "APOLLOHOSP",
        "CIPLA",
        "LUPIN",
        "ZYDUSLIFE",
        "MAXHEALTH",
        "MANKIND",
        "DRREDDY",
        "AUROPHARMA",
        "LAURUSLABS",
        "FORTIS",
        "ASTERDM",
        "BIOCON",
        "ALKEM",
        "GLENMARK",
        "ABBOTINDIA",
        "IPCALAB",
        "AJANTPHARM",
        "ANTHEM",
        "NH",
        "GLAND",
        "GLAXO",
        "JBCHEPHARM",
        "MEDANTA",
        "EMCURE",
        "KIMS",
        "WOCKPHARMA",
        "LALPATHLAB",
        "ACUTAAS",
        "SAILIFE",
        "NEULANDLAB",
        "PPLPHARMA",
        "GRANULES",
        "PFIZER",
        "ERIS",
        "CAPLIPOINT",
        "ONESOURCE",
        "NATCOPHARM",
        "COHANCE",
        "SYNGENE",
        "POLYMED",
        "JUBLPHARMA",
        "RAINBOW",
        "VIJAYA",
        "CONCORDBIO",
        "INDGN",
        "BLUEJET"
      ]
    },
    {
      "name": "Information Technology",
      "medianPe": 27.8,
      "members": [
        "TCS",
        "INFY",
        "HCLTECH",
        "TECHM",
        "LTM",
        "OFSS",
        "PERSISTENT",
        "COFORGE",
        "MPHASIS",
        "LTTS",
        "HEXT",
        "IKS",
        "TATATECH",
        "NETWEB",
        "TATAELXSI",
        "AFFLE",
        "SAGILITY",
        "KPITTECH",
        "ZENSARTECH",
        "INTELLECT",
        "CYIENT",
        "SONATSOFTW",
        "NEWGEN",
        "BSOFT",
        "MAPMYINDIA",
        "LATENTVIEW"
      ]
    },
    {
      "name": "Media Entertainment & Publication",
      "medianPe": 40.9,
      "members": [
        "SUNTV",
        "PVRINOX",
        "ZEEL",
        "SAREGAMA"
      ]
    },
    {
      "name": "Metals & Mining",
      "medianPe": 20.1,
      "members": [
        "ADANIENT",
        "JSWSTEEL",
        "TATASTEEL",
        "HINDZINC",
        "HINDALCO",
        "JINDALSTEL",
        "VEDL",
        "LLOYDSME",
        "NMDC",
        "SAIL",
        "NATIONALUM",
        "JSL",
        "HINDCOPPER",
        "GMDCLTD",
        "SARDAEN",
        "GRAVITA",
        "NSLNISP",
        "JAINREC"
      ]
    },
    {
      "name": "Oil Gas & Consumable Fuels",
      "medianPe": 13.2,
      "members": [
        "RELIANCE",
        "ONGC",
        "COALINDIA",
        "IOC",
        "BPCL",
        "GAIL",
        "HINDPETRO",
        "ATGL",
        "OIL",
        "AEGISLOG",
        "PETRONET",
        "AEGISVOPAK",
        "MRPL",
        "IGL",
        "CASTROLIND",
        "CHENNPETRO",
        "MGL"
      ]
    },
    {
      "name": "Power",
      "medianPe": 33.2,
      "members": [
        "ADANIPOWER",
        "NTPC",
        "POWERGRID",
        "ADANIGREEN",
        "ADANIENSOL",
        "TATAPOWER",
        "JSWENERGY",
        "NHPC",
        "NTPCGREEN",
        "TORNTPOWER",
        "NLCINDIA",
        "SJVN",
        "ACMESOLAR",
        "CESC",
        "NAVA",
        "JPPOWER",
        "RPOWER"
      ]
    },
    {
      "name": "Realty",
      "medianPe": 35.8,
      "members": [
        "DLF",
        "LODHA",
        "PHOENIXLTD",
        "PRESTIGE",
        "OBEROIRLTY",
        "GODREJPROP",
        "ANANTRAJ",
        "BRIGADE",
        "SOBHA",
        "ABREL",
        "SIGNATURE"
      ]
    },
    {
      "name": "Services",
      "medianPe": 28.3,
      "members": [
        "ADANIPORTS",
        "INDIGO",
        "GMRAIRPORT",
        "JSWINFRA",
        "DELHIVERY",
        "CONCOR",
        "REDINGTON",
        "GESHIP",
        "FSL",
        "ECLERX",
        "IGIL",
        "SCI",
        "BLUEDART",
        "MMTC"
      ]
    },
    {
      "name": "Telecommunication",
      "medianPe": 44.9,
      "members": [
        "BHARTIARTL",
        "IDEA",
        "INDUSTOWER",
        "BHARTIHEXA",
        "TATACOMM",
        "HFCL",
        "ITI",
        "RAILTEL",
        "TEJASNET",
        "TTML"
      ]
    },
    {
      "name": "Textiles",
      "medianPe": 44.1,
      "members": [
        "PAGEIND",
        "KPRMILL",
        "VTL",
        "WELSPUNLIV",
        "TRIDENT"
      ]
    }
  ]
}